data_analysis_package/__init__.py
data_analysis_package/data_cleaning.py
data_analysis_package/data_visualization.py
data_analysis_package/statistical_analysis.py
unique_package_name-0.1.0.dist-info/METADATA
unique_package_name-0.1.0.dist-info/WHEEL
unique_package_name-0.1.0.dist-info/top_level.txt
unique_package_name-0.1.0.dist-info/RECORD
